queue_local/__init__.py
queue_local/src/__init__.py
queue_local/src/database_queue.py
queue_local/src/our_queue.py
queue_local-0.1.0.dist-info/METADATA
queue_local-0.1.0.dist-info/WHEEL
queue_local-0.1.0.dist-info/top_level.txt
queue_local-0.1.0.dist-info/RECORD
