Metadata-Version: 2.1
Name: queue-local
Version: 0.1.0
Home-page: https://github.com/circles-zone/queue-local-python-package
Author: Circles
Author-email: info@circles.life
Classifier: Programming Language :: Python :: 3
Classifier: License :: Other/Proprietary License
Classifier: Operating System :: OS Independent
